waybackeasy/__init__.py
waybackeasy/waybackeasy.py
waybackeasy/tests/__init__.py
waybackeasy/tests/test_waybackeasy.py
waybackeasy-1.0.4.dist-info/LICENSE
waybackeasy-1.0.4.dist-info/METADATA
waybackeasy-1.0.4.dist-info/WHEEL
waybackeasy-1.0.4.dist-info/top_level.txt
waybackeasy-1.0.4.dist-info/RECORD
