Metadata-Version: 2.1
Name: waybackeasy
Version: 1.0.4
Summary: The insanely simple way to interface with the Waybackmachine.
Home-page: https://github.com/JohannesSeikowsky/waybackeasy
Author: Johannes Seikowsky
Author-email: jseikowsky@gmail.com
License: UNKNOWN
Platform: UNKNOWN
Classifier: Programming Language :: Python :: 3
Classifier: License :: OSI Approved :: MIT License
Classifier: Operating System :: OS Independent
Requires-Dist: requests (>=1.5.0)
